dragonfile/__init__.py
dragonfile/fileToCsv.py
dragonfile/lenColumns.py
dragonfile/readFile.py
dragonfile/readFileRename.py
dragonfile/readFileSetPeriod.py
dragonfile/readValues.py
tests/__init__.py
dragonfile-1.0.8.dist-info/LICENSE
dragonfile-1.0.8.dist-info/METADATA
dragonfile-1.0.8.dist-info/WHEEL
dragonfile-1.0.8.dist-info/top_level.txt
dragonfile-1.0.8.dist-info/RECORD
